Filytics/__init__.py
Filytics/analyzer.py
Filytics/cli.py
Filytics/reporter.py
Filytics/treeview.py
Filytics/utils.py
filytics-1.0.0.dist-info/licenses/LICENSE
filytics-1.0.0.dist-info/METADATA
filytics-1.0.0.dist-info/WHEEL
filytics-1.0.0.dist-info/entry_points.txt
filytics-1.0.0.dist-info/top_level.txt
filytics-1.0.0.dist-info/RECORD
