Metadata-Version: 2.4
Name: Filytics
Version: 1.0.0
Summary: File and folder statistics analyzer CLI tool
Home-page: https://github.com/oaslananka/Filytics
Author: oaslananka
Author-email: admin@oaslananka.dev
Classifier: Programming Language :: Python :: 3
Classifier: License :: OSI Approved :: MIT License
License-File: LICENSE
Requires-Dist: tabulate
Dynamic: author
Dynamic: author-email
Dynamic: classifier
Dynamic: description
Dynamic: description-content-type
Dynamic: home-page
Dynamic: license-file
Dynamic: requires-dist
Dynamic: summary
